.gitignore
AUTHORS
LICENSE
README.md
setup.py
test/testCouchDB.py
wallaby/__init__.py
wallaby/backends/__init__.py
wallaby/backends/couchdb/__init__.py
wallaby_backend_couchdb.egg-info/PKG-INFO
wallaby_backend_couchdb.egg-info/SOURCES.txt
wallaby_backend_couchdb.egg-info/dependency_links.txt
wallaby_backend_couchdb.egg-info/requires.txt
wallaby_backend_couchdb.egg-info/top_level.txt